<lido:lido xmlns:lido="http://www.lido-schema.org" xmlns:xsi="http://www.w3.org/2001/XMLSchema-instance" xsi:schemaLocation="http://www.lido-schema.org         http://www.lido-schema.org/schema/v1.0/lido-v1.0.xsd"><lido:lidoRecID lido:type="http://terminology.lido-schema.org/lido00100">DE-MUS-027614/lido/81142</lido:lidoRecID><lido:objectPublishedID lido:type="http://terminology.lido-schema.org/lido00100" lido:source="https://www.kunsthalle-bremen.de/">DE-MUS-027614/object/81142</lido:objectPublishedID><lido:descriptiveMetadata xml:lang="de">
         <lido:objectClassificationWrap>
            <lido:objectWorkTypeWrap>
               <lido:objectWorkType>
                  <lido:conceptID lido:type="http://terminology.lido-schema.org/lido00099">http://vocab.getty.edu/aat/300041273</lido:conceptID>
                  <lido:term>Druckgraphik</lido:term>
                  <lido:term lido:addedSearchTerm="yes">Druckgraphik</lido:term>
               </lido:objectWorkType>
            </lido:objectWorkTypeWrap>
            <lido:classificationWrap>
               <lido:classification lido:type="Objektklassifikation" lido:sortorder="1">
                  <lido:conceptID lido:type="http://terminology.lido-schema.org/lido00099">http://vocab.getty.edu/aat/300041273</lido:conceptID>
                  <lido:term>Druckgraphik</lido:term>
                  <lido:term lido:addedSearchTerm="yes">Druckgraphik</lido:term>
               </lido:classification>
            </lido:classificationWrap>
         </lido:objectClassificationWrap>
         <lido:objectIdentificationWrap>
            <lido:titleWrap>
               <lido:titleSet lido:type="Titel" lido:sortorder="1">
                  <lido:appellationValue lido:pref="preferred">Justus Jonas, Michael Celius u.a., "Vom Christlichen Abschied aus diesem tödlichen Leben des Ehrwürdigen Herrn D. Martini Lutheri", Wittenberg 1546</lido:appellationValue>
               </lido:titleSet>
            </lido:titleWrap>
            
            <lido:repositoryWrap>
               <lido:repositorySet lido:type="http://terminology.lido-schema.org/lido00475">
                  <lido:repositoryName>
                     <lido:legalBodyID lido:type="http://terminology.lido-schema.org/lido00099" lido:source="ISIL (ISO 15511)">http://ld.zdb-services.de/resource/organisations/DE-MUS-027614</lido:legalBodyID>
                     <lido:legalBodyName>
                        <lido:appellationValue>Kunsthalle Bremen</lido:appellationValue>
                        <lido:appellationValue>Bremen, Kunsthalle Bremen</lido:appellationValue>
                     </lido:legalBodyName>
                     <lido:legalBodyWeblink lido:formatResource="text/html">https://www.kunsthalle-bremen.de/</lido:legalBodyWeblink>
                  </lido:repositoryName>
                  <lido:repositoryLocation>
                     <lido:placeID lido:type="http://terminology.lido-schema.org/lido00099">https://d-nb.info/gnd/4008135-7</lido:placeID>
                     <lido:placeID lido:type="http://terminology.lido-schema.org/lido00099">http://www.geonames.org/2944387</lido:placeID>
                     <lido:placeID lido:type="http://terminology.lido-schema.org/lido00099">http://vocab.getty.edu/page/tgn/7005286</lido:placeID>
                     <lido:namePlaceSet>
                        <lido:appellationValue>Bremen</lido:appellationValue>
                     </lido:namePlaceSet>
                  </lido:repositoryLocation>
               </lido:repositorySet>
            </lido:repositoryWrap>
            
            
         </lido:objectIdentificationWrap>
         <lido:eventWrap>
            <lido:eventSet lido:sortorder="1">
               <lido:event>
                  <lido:eventType>
                     <lido:conceptID lido:type="http://terminology.lido-schema.org/lido00099" lido:source="http://terminology.lido-schema.org/eventType">http://terminology.lido-schema.org/lido00007</lido:conceptID>
                     <lido:term lido:addedSearchTerm="no">Herstellung</lido:term>
                  </lido:eventType>
                  <lido:eventActor lido:sortorder="5">
                     <lido:displayActorInRole>alternative Zuschreibung Lucas Cranach d. Ä. (*Kronach/Coburg 1472 - † Weimar 1553), Formschneider</lido:displayActorInRole>
                     <lido:actorInRole>
                        <lido:actor>
                           <lido:actorID lido:pref="preferred" lido:type="http://terminology.lido-schema.org/lido00099" lido:source="http://d-nb.info/gnd/">http://d-nb.info/gnd/118522582</lido:actorID>
                           <lido:nameActorSet>
                              <lido:appellationValue lido:pref="preferred" lido:encodinganalog="http://d-nb.info/standards/elementset/gnd#preferredNameForThePerson">Cranach, Lucas, der Ältere</lido:appellationValue>
                              <lido:appellationValue lido:pref="alternative" lido:encodinganalog="http://d-nb.info/standards/elementset/gnd#variantForThePerson">Cranach, Lucas, d. Ä.</lido:appellationValue>
                              <lido:appellationValue lido:pref="alternative" lido:encodinganalog="http://d-nb.info/standards/elementset/gnd#variantForThePerson">Cranach, Lukas d.Ä.</lido:appellationValue>
                              <lido:appellationValue lido:pref="alternative" lido:encodinganalog="http://d-nb.info/standards/elementset/gnd#variantForThePerson">Cranach, Lucas st.</lido:appellationValue>
                              <lido:appellationValue lido:pref="alternative" lido:encodinganalog="http://d-nb.info/standards/elementset/gnd#variantForThePerson">Cranach, Lucas, the elder</lido:appellationValue>
                              <lido:appellationValue lido:pref="alternative" lido:encodinganalog="http://d-nb.info/standards/elementset/gnd#variantForThePerson">Sunder, Lucas</lido:appellationValue>
                              <lido:appellationValue lido:pref="alternative" lido:encodinganalog="http://d-nb.info/standards/elementset/gnd#variantForThePerson">Sunder, Lukas</lido:appellationValue>
                              <lido:appellationValue lido:pref="alternative" lido:encodinganalog="http://d-nb.info/standards/elementset/gnd#variantForThePerson">Sünder, Lukas</lido:appellationValue>
                              <lido:appellationValue lido:pref="alternative" lido:encodinganalog="http://d-nb.info/standards/elementset/gnd#variantForThePerson">Sünder, Lucas</lido:appellationValue>
                              <lido:appellationValue lido:pref="alternative" lido:encodinganalog="http://d-nb.info/standards/elementset/gnd#variantForThePerson">Cranach, Lukas, der Ältere</lido:appellationValue>
                              <lido:appellationValue lido:pref="alternative" lido:encodinganalog="http://d-nb.info/standards/elementset/gnd#variantForThePerson">Kurānaha</lido:appellationValue>
                              <lido:appellationValue lido:pref="alternative" lido:encodinganalog="http://d-nb.info/standards/elementset/gnd#variantForThePerson">Kranach, Lukas</lido:appellationValue>
                              <lido:appellationValue lido:pref="alternative" lido:encodinganalog="http://d-nb.info/standards/elementset/gnd#variantForThePerson">Kranach, Lucas</lido:appellationValue>
                              <lido:appellationValue lido:pref="alternative" lido:encodinganalog="http://d-nb.info/standards/elementset/gnd#variantForThePerson">Cranach, Lukas</lido:appellationValue>
                              <lido:appellationValue lido:pref="alternative" lido:encodinganalog="http://d-nb.info/standards/elementset/gnd#variantForThePerson">Müller, Lucas</lido:appellationValue>
                              <lido:appellationValue lido:pref="alternative" lido:encodinganalog="http://d-nb.info/standards/elementset/gnd#variantForThePerson">Sunder-Maler, Lucas</lido:appellationValue>
                              <lido:appellationValue lido:pref="alternative" lido:encodinganalog="http://d-nb.info/standards/elementset/gnd#variantForThePerson">Maler, Lucas</lido:appellationValue>
                              <lido:appellationValue lido:pref="alternative" lido:encodinganalog="http://d-nb.info/standards/elementset/gnd#variantForThePerson">Moller, Lucas</lido:appellationValue>
                              <lido:appellationValue lido:pref="alternative" lido:encodinganalog="http://d-nb.info/standards/elementset/gnd#variantForThePerson">Cronach, Lucas</lido:appellationValue>
                              <lido:appellationValue lido:pref="alternative">Cranach d. Ä., Lucas</lido:appellationValue>
                           </lido:nameActorSet>
                           <lido:vitalDatesActor>
                              <lido:earliestDate lido:type="Geburtsdatum" lido:encodinganalog="http://d-nb.info/standards/elementset/gnd#dateOfBirth">1472</lido:earliestDate>
                              <lido:latestDate lido:type="Sterbedatum" lido:encodinganalog="http://d-nb.info/standards/elementset/gnd#dateOfDeath">1553-10-16</lido:latestDate>
                           </lido:vitalDatesActor>
                        </lido:actor>
                        <lido:roleActor>
                           <lido:conceptID lido:type="http://terminology.lido-schema.org/lido00099" lido:source="AAT">http://vocab.getty.edu/aat/300025178</lido:conceptID>
                           <lido:term>Formschneider</lido:term>
                           <lido:term lido:addedSearchTerm="yes">Formschneider</lido:term>
                        </lido:roleActor>
                        <lido:attributionQualifierActor>alternative Zuschreibung</lido:attributionQualifierActor>
                        <lido:attributionQualifierActor>alternative Zuschreibung</lido:attributionQualifierActor>
                     </lido:actorInRole>
                  </lido:eventActor>
                  <lido:eventActor lido:sortorder="1">
                     <lido:displayActorInRole>Anonym, Formschneider</lido:displayActorInRole>
                     <lido:actorInRole>
                        <lido:actor>
                           <lido:nameActorSet>
                              <lido:appellationValue lido:pref="preferred">Anonym</lido:appellationValue>
                           </lido:nameActorSet>
                        </lido:actor>
                        <lido:roleActor>
                           <lido:conceptID lido:type="http://terminology.lido-schema.org/lido00099" lido:source="AAT">http://vocab.getty.edu/aat/300025178</lido:conceptID>
                           <lido:term>Formschneider</lido:term>
                           <lido:term lido:addedSearchTerm="yes">Formschneider</lido:term>
                        </lido:roleActor>
                     </lido:actorInRole>
                  </lido:eventActor>
                  <lido:eventDate>
                     <lido:displayDate>1505-1546</lido:displayDate>
                     <lido:date>
                        <lido:earliestDate>1505</lido:earliestDate>
                        <lido:latestDate>1546</lido:latestDate>
                     </lido:date>
                  </lido:eventDate>
                  <lido:eventMaterialsTech lido:sortorder="1">
                     <lido:displayMaterialsTech>Holzschnitt</lido:displayMaterialsTech>
                     
                  </lido:eventMaterialsTech>
               </lido:event>
            </lido:eventSet>
            <lido:eventSet lido:sortorder="2">
               <lido:event>
                  <lido:eventType>
                     <lido:conceptID lido:type="http://terminology.lido-schema.org/lido00099" lido:source="http://terminology.lido-schema.org/eventType">http://terminology.lido-schema.org/lido00228</lido:conceptID>
                     <lido:term lido:addedSearchTerm="no">Veröffentlichung</lido:term>
                  </lido:eventType>
                  <lido:eventActor lido:sortorder="10">
                     <lido:displayActorInRole>Georg Rhau (*Eisfeld 1488 - † 1548), Verleger</lido:displayActorInRole>
                     <lido:actorInRole>
                        <lido:actor>
                           <lido:actorID lido:pref="preferred" lido:type="http://terminology.lido-schema.org/lido00099" lido:source="http://d-nb.info/gnd/">http://d-nb.info/gnd/115690387</lido:actorID>
                           <lido:nameActorSet>
                              <lido:appellationValue lido:pref="preferred" lido:encodinganalog="http://d-nb.info/standards/elementset/gnd#preferredNameForThePerson">Rhau, Georg</lido:appellationValue>
                              <lido:appellationValue lido:pref="alternative" lido:encodinganalog="http://d-nb.info/standards/elementset/gnd#variantForThePerson">Rhauvus, Georgius</lido:appellationValue>
                              <lido:appellationValue lido:pref="alternative" lido:encodinganalog="http://d-nb.info/standards/elementset/gnd#variantForThePerson">Rhauus, Georgius</lido:appellationValue>
                              <lido:appellationValue lido:pref="alternative" lido:encodinganalog="http://d-nb.info/standards/elementset/gnd#variantForThePerson">Raw, Georg</lido:appellationValue>
                              <lido:appellationValue lido:pref="alternative" lido:encodinganalog="http://d-nb.info/standards/elementset/gnd#variantForThePerson">Rhaw, Jorg</lido:appellationValue>
                              <lido:appellationValue lido:pref="alternative" lido:encodinganalog="http://d-nb.info/standards/elementset/gnd#variantForThePerson">Rhav, G.</lido:appellationValue>
                              <lido:appellationValue lido:pref="alternative" lido:encodinganalog="http://d-nb.info/standards/elementset/gnd#variantForThePerson">Rauch, G.</lido:appellationValue>
                              <lido:appellationValue lido:pref="alternative" lido:encodinganalog="http://d-nb.info/standards/elementset/gnd#variantForThePerson">Rhavus, Georgius</lido:appellationValue>
                              <lido:appellationValue lido:pref="alternative" lido:encodinganalog="http://d-nb.info/standards/elementset/gnd#variantForThePerson">Rhau, Georgius</lido:appellationValue>
                              <lido:appellationValue lido:pref="alternative" lido:encodinganalog="http://d-nb.info/standards/elementset/gnd#variantForThePerson">Rhawe, Georg</lido:appellationValue>
                              <lido:appellationValue lido:pref="alternative" lido:encodinganalog="http://d-nb.info/standards/elementset/gnd#variantForThePerson">Rhaw, Georg</lido:appellationValue>
                              <lido:appellationValue lido:pref="alternative" lido:encodinganalog="http://d-nb.info/standards/elementset/gnd#variantForThePerson">Rau, Georg</lido:appellationValue>
                           </lido:nameActorSet>
                           <lido:vitalDatesActor>
                              <lido:earliestDate lido:type="Geburtsdatum" lido:encodinganalog="http://d-nb.info/standards/elementset/gnd#dateOfBirth">1488</lido:earliestDate>
                              <lido:latestDate lido:type="Sterbedatum" lido:encodinganalog="http://d-nb.info/standards/elementset/gnd#dateOfDeath">1548-08-06</lido:latestDate>
                           </lido:vitalDatesActor>
                        </lido:actor>
                        <lido:roleActor>
                           <lido:conceptID lido:type="http://terminology.lido-schema.org/lido00099" lido:source="AAT">http://vocab.getty.edu/aat/300025574</lido:conceptID>
                           <lido:term>Verleger</lido:term>
                        </lido:roleActor>
                     </lido:actorInRole>
                  </lido:eventActor>
                  <lido:eventDate>
                     <lido:displayDate>1546</lido:displayDate>
                     <lido:date>
                        <lido:earliestDate>1546</lido:earliestDate>
                        <lido:latestDate>1546</lido:latestDate>
                     </lido:date>
                  </lido:eventDate>
                  <lido:eventPlace lido:sortorder="1">
                     <lido:displayPlace>Wittenberg</lido:displayPlace>
                     <lido:place>
                        <lido:placeID lido:type="http://terminology.lido-schema.org/lido00099" lido:source="GND">http://d-nb.info/gnd/4066640-2</lido:placeID>
                        <lido:namePlaceSet>
                           <lido:appellationValue>Wittenberg</lido:appellationValue>
                        </lido:namePlaceSet>
                     </lido:place>
                  </lido:eventPlace>
               </lido:event>
            </lido:eventSet>
            <lido:eventSet lido:sortorder="1">
               <lido:event>
                  <lido:eventType>
                     <lido:conceptID lido:type="http://terminology.lido-schema.org/lido00099" lido:source="http://terminology.lido-schema.org/eventType">http://terminology.lido-schema.org/lido00484</lido:conceptID>
                     <lido:term lido:addedSearchTerm="no">Herstellung</lido:term>
                  </lido:eventType>
                  <lido:eventDate>
                     <lido:displayDate>um 1513</lido:displayDate>
                     <lido:date>
                        <lido:earliestDate>1513</lido:earliestDate>
                        <lido:latestDate>1513</lido:latestDate>
                     </lido:date>
                  </lido:eventDate>
               </lido:event>
            </lido:eventSet>
         </lido:eventWrap>
         <lido:objectRelationWrap>
            
            <lido:relatedWorksWrap>
               <lido:relatedWorkSet>
                  
                  <lido:relatedWorkRelType>
                     <lido:conceptID lido:type="http://terminology.lido-schema.org/lido00100">R3i_realises</lido:conceptID>
                  </lido:relatedWorkRelType>
               </lido:relatedWorkSet>
               <lido:relatedWorkSet>
                  
                  <lido:relatedWorkRelType>
                     <lido:conceptID lido:type="http://terminology.lido-schema.org/lido00100">R3i_realises</lido:conceptID>
                  </lido:relatedWorkRelType>
               </lido:relatedWorkSet>
               <lido:relatedWorkSet>
                  <lido:relatedWork>
                     <lido:displayObject>30563, Lucas Cranach d. Ä. (1472 - 16.10.1553)/ Georg Rhau (1488 - 1548), Bildnis Martin Luther, aus: Justus Jonas, Michael Celius u.a., "Vom Christlichen Abschied aus diesem tödlichen Leben des Ehrwürdigen Herrn D. Martini Lutheri", Wittenberg 1546, Herstellung der Druckplatte: 1505-1546/ Herstellung der Druckplatte: um 1513</lido:displayObject>
                     <lido:object>
                        <lido:objectID lido:type="http://terminology.lido-schema.org/lido00100">DE-MUS-027614/object/68855</lido:objectID>
                        
                     </lido:object>
                  </lido:relatedWork>
                  <lido:relatedWorkRelType>
                     <lido:conceptID lido:type="http://terminology.lido-schema.org/lido00100" lido:source="http://www.cidoc-crm.org/rdfs/cidoc_crm_v5.0.4_official_release.rdfs">P46_is_composed_of</lido:conceptID>
                     <lido:term>hat Teil</lido:term>
                  </lido:relatedWorkRelType>
               </lido:relatedWorkSet>
            </lido:relatedWorksWrap>
         </lido:objectRelationWrap>
      </lido:descriptiveMetadata><lido:administrativeMetadata xml:lang="de">
         <lido:rightsWorkWrap>
            <lido:rightsWorkSet lido:sortorder="1">
               <lido:rightsType>
                  <lido:conceptID lido:type="http://terminology.lido-schema.org/lido00099">http://creativecommons.org/publicdomain/mark/1.0/</lido:conceptID>
                  <lido:term>Public Domain Mark 1.0</lido:term>
               </lido:rightsType>
            </lido:rightsWorkSet>
         </lido:rightsWorkWrap>
         <lido:recordWrap>
            <lido:recordID lido:type="http://terminology.lido-schema.org/lido00100">81142</lido:recordID>
            <lido:recordType>
               <lido:conceptID lido:type="http://terminology.lido-schema.org/lido00099" lido:source="http://terminology.lido-schema.org">http://terminology.lido-schema.org/lido00453</lido:conceptID>
               <lido:term>Serie</lido:term>
            </lido:recordType>
            <lido:recordSource>
               <lido:legalBodyID lido:type="http://terminology.lido-schema.org/lido00099">http://ld.zdb-services.de/resource/organisations/DE-MUS-027614</lido:legalBodyID>
               <lido:legalBodyName>
                  <lido:appellationValue>Kunsthalle Bremen</lido:appellationValue>
               </lido:legalBodyName>
               <lido:legalBodyWeblink lido:formatResource="text/html">https://www.kunsthalle-bremen.de/</lido:legalBodyWeblink>
            </lido:recordSource>
            <lido:recordRights>
               <lido:rightsType>
                  <lido:conceptID lido:type="http://terminology.lido-schema.org/lido00099">http://creativecommons.org/publicdomain/zero/1.0/</lido:conceptID>
                  <lido:term>CC0 1.0 Universell</lido:term>
               </lido:rightsType>
               <lido:rightsHolder>
                  <lido:legalBodyID lido:type="http://terminology.lido-schema.org/lido00099" lido:source="ISIL (ISO 15511)">http://ld.zdb-services.de/resource/organisations/DE-MUS-027614</lido:legalBodyID>
                  <lido:legalBodyName>
                     <lido:appellationValue>Kunsthalle Bremen</lido:appellationValue>
                  </lido:legalBodyName>
                  <lido:legalBodyWeblink lido:formatResource="text/html">https://www.kunsthalle-bremen.de/</lido:legalBodyWeblink>
               </lido:rightsHolder>
            </lido:recordRights>
            <lido:recordInfoSet>
               <lido:recordInfoLink>https://onlinekatalog.kunsthalle-bremen.de/DE-MUS-027614/object/81142</lido:recordInfoLink>
               <lido:recordMetadataDate>2025-02-11T15:41:59.986</lido:recordMetadataDate>
            </lido:recordInfoSet>
         </lido:recordWrap>
         
      </lido:administrativeMetadata></lido:lido>